pplayer/__init__.py
pplayer/player.py
pplayer-0.1.2.dist-info/METADATA
pplayer-0.1.2.dist-info/WHEEL
pplayer-0.1.2.dist-info/top_level.txt
pplayer-0.1.2.dist-info/RECORD
