Metadata-Version: 2.1
Name: pplayer
Version: 0.1.2
Summary: Player package for your pygame game
Author: Aynu
Classifier: Programming Language :: Python :: 3
Classifier: License :: OSI Approved :: MIT License
Classifier: Operating System :: OS Independent
Classifier: Development Status :: 3 - Alpha
Classifier: Intended Audience :: Developers
Classifier: Topic :: Games/Entertainment
Requires-Python: >=3.6
Requires-Dist: pygame
